pysaint/__init__.py
pysaint/api.py
pysaint/constants.py
pysaint/parser.py
pysaint/saint.py
pysaint/sap_event_queue.py
pysaint/utils.py
pysaint-1.4.4.dist-info/.DS_Store
pysaint-1.4.4.dist-info/METADATA
pysaint-1.4.4.dist-info/RECORD
pysaint-1.4.4.dist-info/WHEEL
pysaint-1.4.4.dist-info/entry_points.txt
pysaint-1.4.4.dist-info/top_level.txt
scripts/__init__.py
scripts/cli.py
