Metadata-Version: 2.1
Name: pysaint
Version: 1.4.4
Summary: Python module for saint.ssu.ac.kr
Home-page: https://github.com/gomjellie/pysaint
Author: gomjellie
Author-email: gomjellie@gmail.com
License: MIT
Download-URL: https://pypi.python.org/pypi/pysaint
Platform: Posix; MacOS X; Windows
Classifier: Development Status :: 5 - Production/Stable
Classifier: Topic :: Software Development :: Testing
Classifier: Intended Audience :: Developers
Classifier: License :: OSI Approved :: MIT License
Classifier: Operating System :: OS Independent
Classifier: Programming Language :: Python
Classifier: Programming Language :: Python :: 2.6
Classifier: Programming Language :: Python :: 2.7
Classifier: Programming Language :: Python :: 3.3
Classifier: Programming Language :: Python :: 3.4
Classifier: Programming Language :: Python :: 3.5
Classifier: Programming Language :: Python :: 3.6
Classifier: Programming Language :: Python :: Implementation :: PyPy
Requires-Dist: beautifulsoup4 (==4.6.0)
Requires-Dist: bs4 (==0.0.1)
Requires-Dist: certifi (==2018.1.18)
Requires-Dist: chardet (==3.0.4)
Requires-Dist: click (==6.7)
Requires-Dist: idna (==2.6)
Requires-Dist: lxml (==4.1.1)
Requires-Dist: requests (==2.18.4)
Requires-Dist: urllib3 (==1.22)
